LICENSE
MANIFEST.in
README.md
setup.py
src/peakrdl_halcpp/__about__.py
src/peakrdl_halcpp/__init__.py
src/peakrdl_halcpp/__peakrdl__.py
src/peakrdl_halcpp/exporter.py
src/peakrdl_halcpp/halnode.py
src/peakrdl_halcpp/halutils.py
src/peakrdl_halcpp.egg-info/PKG-INFO
src/peakrdl_halcpp.egg-info/SOURCES.txt
src/peakrdl_halcpp.egg-info/dependency_links.txt
src/peakrdl_halcpp.egg-info/entry_points.txt
src/peakrdl_halcpp.egg-info/requires.txt
src/peakrdl_halcpp.egg-info/top_level.txt
src/peakrdl_halcpp/include/__init__.py
src/peakrdl_halcpp/include/addrmap_node.h
src/peakrdl_halcpp/include/arch_io.h
src/peakrdl_halcpp/include/array_nodes.h
src/peakrdl_halcpp/include/field_node.h
src/peakrdl_halcpp/include/halcpp_base.h
src/peakrdl_halcpp/include/halcpp_utils.h
src/peakrdl_halcpp/include/mem_node.h
src/peakrdl_halcpp/include/reg_node.h
src/peakrdl_halcpp/include/regfile_node.h
src/peakrdl_halcpp/templates/__init__.py
src/peakrdl_halcpp/templates/addrmap.h.j2